miniircd.py
miniircd-2.3.dist-info/LICENSE
miniircd-2.3.dist-info/METADATA
miniircd-2.3.dist-info/WHEEL
miniircd-2.3.dist-info/entry_points.txt
miniircd-2.3.dist-info/top_level.txt
miniircd-2.3.dist-info/RECORD
