Metadata-Version: 2.1
Name: miniircd
Version: 2.3
Summary: A very simple Internet Relay Chat (IRC) server
Home-page: https://github.com/jrosdahl/miniircd
Author: Joel Rosdahl
Author-email: joel@rosdahl.net
Maintainer: Joel Rosdahl
Maintainer-email: joel@rosdahl.net
License: GPLv2
Keywords: IRC
Classifier: Development Status :: 6 - Mature
Classifier: Intended Audience :: Developers
Classifier: Intended Audience :: System Administrators
Classifier: License :: OSI Approved :: GNU General Public License v2 (GPLv2)
Classifier: Natural Language :: English
Classifier: Operating System :: OS Independent
Classifier: Programming Language :: Python :: 3 :: Only
Classifier: Programming Language :: Python :: 3.6
Classifier: Programming Language :: Python :: 3.7
Classifier: Programming Language :: Python :: 3.8
Classifier: Programming Language :: Python :: 3.9
Classifier: Programming Language :: Python :: 3.10
Classifier: Programming Language :: Python :: 3.11
Classifier: Programming Language :: Python :: Implementation :: CPython
Classifier: Programming Language :: Python :: Implementation :: PyPy
License-File: LICENSE
Provides-Extra: dev
Requires-Dist: build; extra == "dev"
Requires-Dist: flake8; extra == "dev"
Requires-Dist: mypy; extra == "dev"
Requires-Dist: nose; extra == "dev"
Requires-Dist: twine; extra == "dev"
